Perceptron_ndsnajam/__init__.py
Perceptron_ndsnajam/perceptron.py
Perceptron_ndsnajam-0.0.2.dist-info/LICENSE
Perceptron_ndsnajam-0.0.2.dist-info/METADATA
Perceptron_ndsnajam-0.0.2.dist-info/WHEEL
Perceptron_ndsnajam-0.0.2.dist-info/top_level.txt
Perceptron_ndsnajam-0.0.2.dist-info/RECORD
